sgfmill/__init__.py
sgfmill/ascii_boards.py
sgfmill/boards.py
sgfmill/common.py
sgfmill/sgf.py
sgfmill/sgf_board_interface.py
sgfmill/sgf_grammar.py
sgfmill/sgf_moves.py
sgfmill/sgf_properties.py
sgfmill-1.1.0.dist-info/DESCRIPTION.rst
sgfmill-1.1.0.dist-info/METADATA
sgfmill-1.1.0.dist-info/RECORD
sgfmill-1.1.0.dist-info/WHEEL
sgfmill-1.1.0.dist-info/metadata.json
sgfmill-1.1.0.dist-info/top_level.txt
