Metadata-Version: 2.0
Name: sgfmill
Version: 1.1.0
Summary: Library for reading and writing files using Smart Game Format (SGF).
Home-page: https://mjw.woodcraft.me.uk/sgfmill/
Author: Matthew Woodcraft
Author-email: matthew@woodcraft.me.uk
License: MIT
Keywords: go,baduk,weiqi,sgf
Platform: UNKNOWN
Classifier: Development Status :: 5 - Production/Stable
Classifier: Intended Audience :: Developers
Classifier: License :: OSI Approved :: MIT License
Classifier: Natural Language :: English
Classifier: Programming Language :: Python :: 3
Classifier: Programming Language :: Python :: 3.2
Classifier: Programming Language :: Python :: 3.3
Classifier: Programming Language :: Python :: 3.4
Classifier: Programming Language :: Python :: 3.5
Classifier: Programming Language :: Python :: 3.6
Classifier: Programming Language :: Python
Classifier: Topic :: Games/Entertainment :: Board Games
Classifier: Topic :: Software Development :: Libraries :: Python Modules
